ProgressPrinter/__init__.py
ProgressPrinter/byte_progress_bar.py
ProgressPrinter/progress_bar.py
ProgressPrinter-0.1.1.dist-info/LICENSE.md
ProgressPrinter-0.1.1.dist-info/METADATA
ProgressPrinter-0.1.1.dist-info/WHEEL
ProgressPrinter-0.1.1.dist-info/top_level.txt
ProgressPrinter-0.1.1.dist-info/RECORD
