Metadata-Version: 2.1
Name: ProgressPrinter
Version: 0.1.1
Summary: Simple library that allows you to add a progress bar to your console output.
Home-page: https://github.com/ElCap1tan/ProgressPrinter
Author: Yannic Wehner
Author-email: yannic.wehner@elcapitan.io
License: MIT
Download-URL: https://github.com/ElCap1tan/ProgressPrinter/archive/v0.1.1.tar.gz
Keywords: terminal,console,shell,progress bar
Platform: UNKNOWN
Classifier: Development Status :: 4 - Beta
Classifier: Intended Audience :: Developers
Classifier: Topic :: Software Development :: Build Tools
Classifier: License :: OSI Approved :: MIT License
Classifier: Programming Language :: Python :: 3
Classifier: Programming Language :: Python :: 3.4
Classifier: Programming Language :: Python :: 3.5
Classifier: Programming Language :: Python :: 3.6
Classifier: Programming Language :: Python :: 3.7
